spaceone/__init__.py
spaceone/monitoring/__init__.py
spaceone/monitoring/conf/__init__.py
spaceone/monitoring/conf/default_escalation_policy.py
spaceone/monitoring/conf/global_conf.py
spaceone/monitoring/conf/proto_conf.py
spaceone/monitoring/conf/router_conf.py
spaceone/monitoring/connector/__init__.py
spaceone/monitoring/connector/datasource_plugin_connector.py
spaceone/monitoring/connector/webhook_plugin_connector.py
spaceone/monitoring/error/__init__.py
spaceone/monitoring/error/alert.py
spaceone/monitoring/error/data_source.py
spaceone/monitoring/error/escalation_policy.py
spaceone/monitoring/error/event_rule.py
spaceone/monitoring/error/maintenance_window.py
spaceone/monitoring/error/metric.py
spaceone/monitoring/error/project_alert_config.py
spaceone/monitoring/error/webhook.py
spaceone/monitoring/info/__init__.py
spaceone/monitoring/info/alert_info.py
spaceone/monitoring/info/common_info.py
spaceone/monitoring/info/data_source_info.py
spaceone/monitoring/info/escalation_policy_info.py
spaceone/monitoring/info/event_info.py
spaceone/monitoring/info/event_rule_info.py
spaceone/monitoring/info/log_info.py
spaceone/monitoring/info/maintenance_window_info.py
spaceone/monitoring/info/metric_info.py
spaceone/monitoring/info/note_info.py
spaceone/monitoring/info/project_alert_config_info.py
spaceone/monitoring/info/webhook_info.py
spaceone/monitoring/interface/__init__.py
spaceone/monitoring/interface/grpc/__init__.py
spaceone/monitoring/interface/grpc/v1/__init__.py
spaceone/monitoring/interface/grpc/v1/alert.py
spaceone/monitoring/interface/grpc/v1/data_source.py
spaceone/monitoring/interface/grpc/v1/escalation_policy.py
spaceone/monitoring/interface/grpc/v1/event.py
spaceone/monitoring/interface/grpc/v1/event_rule.py
spaceone/monitoring/interface/grpc/v1/log.py
spaceone/monitoring/interface/grpc/v1/maintenance_window.py
spaceone/monitoring/interface/grpc/v1/metric.py
spaceone/monitoring/interface/grpc/v1/note.py
spaceone_monitoring-1.12.0.dist-info/METADATA
spaceone_monitoring-1.12.0.dist-info/WHEEL
spaceone_monitoring-1.12.0.dist-info/top_level.txt
spaceone_monitoring-1.12.0.dist-info/RECORD
